{"formatVersion":1,"settings":{"gamesMonth":"2024-02","maxPlayerId":24,"maxGameId":11},"games":[{"id":1,"date":"2024-02-07","players":[9,8,1,7,6,2,3,4,10,5],"selectedPoints":["0","0","0","0","0","0.4","0","0","0","0"],"don":9,"maf1":5,"maf2":7,"sherif":6,"firstKilled":null,"firstKilledGuessPoints":null,"cityWin":false},{"id":2,"date":"2024-02-07","players":[10,6,4,2,1,5,9,8,7,3],"selectedPoints":["0","0","0.3","0","0","0","0","0","0","0.2"],"don":1,"maf1":2,"maf2":7,"sherif":4,"firstKilled":5,"firstKilledGuessPoints":0,"cityWin":false},{"id":3,"date":"2024-02-07","players":[7,4,3,1,6,9,2,10,5,8],"selectedPoints":["0","0","0.2","0.1","0","0","0","0","0","0"],"don":2,"maf1":0,"maf2":7,"sherif":9,"firstKilled":4,"firstKilledGuessPoints":0,"cityWin":false},{"id":4,"date":"2024-02-07","players":[5,3,4,9,1,10,6,7,8,2],"selectedPoints":["0","0","0","0","0.3","0","0","0","0","0"],"don":9,"maf1":0,"maf2":4,"sherif":7,"firstKilled":8,"firstKilledGuessPoints":0,"cityWin":false},{"id":5,"date":"2024-02-08","players":[11,12,13,5,2,14,15,18,16,17],"selectedPoints":["0","0","0","0","0","0","0.1","0.3","0","0"],"don":8,"maf1":0,"maf2":3,"sherif":1,"firstKilled":6,"firstKilledGuessPoints":0.25,"cityWin":true},{"id":6,"date":"2024-02-08","players":[12,18,16,11,17,14,15,2,13,5],"selectedPoints":["0","0","0","0","0","0","0","0","0","0.2"],"don":3,"maf1":0,"maf2":4,"sherif":8,"firstKilled":1,"firstKilledGuessPoints":0,"cityWin":true},{"id":7,"date":"2024-02-08","players":[13,12,2,14,15,5,17,18,16,11],"selectedPoints":["0","0","0","0","0","0","0.1","0","0","0"],"don":0,"maf1":1,"maf2":7,"sherif":9,"firstKilled":8,"firstKilledGuessPoints":0,"cityWin":true},{"id":8,"date":"2024-02-08","players":[5,15,13,18,16,2,14,11,12,17],"selectedPoints":["0.1","0","0.2","0","0.1","0","0","0","0","0"],"don":5,"maf1":6,"maf2":7,"sherif":9,"firstKilled":1,"firstKilledGuessPoints":0,"cityWin":true},{"id":9,"date":"2024-02-15","players":[19,12,20,21,13,22,14,23,11,24],"selectedPoints":["0","0","0","0.1","0","0","0.2","0","0","0"],"don":3,"maf1":1,"maf2":6,"sherif":4,"firstKilled":4,"firstKilledGuessPoints":0.25,"cityWin":false},{"id":10,"date":"2024-02-15","players":[13,24,21,14,12,23,11,19,22,20],"selectedPoints":["0","0","0.3","0","0","0.1","0","0","0","0"],"don":5,"maf1":2,"maf2":7,"sherif":9,"firstKilled":1,"firstKilledGuessPoints":0,"cityWin":false},{"id":11,"date":"2024-02-15","players":[22,19,13,12,24,20,21,14,23,11],"selectedPoints":["0","0","0","0","0","0","0","0","0","0.1"],"don":0,"maf1":1,"maf2":3,"sherif":2,"firstKilled":null,"firstKilledGuessPoints":null,"cityWin":true}],"players":[{"id":1,"name":"г-жа Юник","nameHistory":[{"nameChangeId":1,"name":"г-жа Юник","date":1708281616581}]},{"id":2,"name":"г-н Алхимик","nameHistory":[{"nameChangeId":1,"name":"г-н Алхимик","date":1708281638072}]},{"id":3,"name":"г-н Масяня","nameHistory":[{"nameChangeId":1,"name":"г-н Масяня","date":1708281662644}]},{"id":4,"name":"г-жа Франц","nameHistory":[{"nameChangeId":1,"name":"г-жа Франц","date":1708281678986}]},{"id":5,"name":"г-н Джон Ву","nameHistory":[{"nameChangeId":1,"name":"г-н Джон Ву","date":1708281693267}]},{"id":6,"name":"г-н Акуна Матата","nameHistory":[{"nameChangeId":1,"name":"г-н Акуна Матата","date":1708281708288}]},{"id":7,"name":"г-н Венский Опер","nameHistory":[{"nameChangeId":1,"name":"г-н Венский Опер","date":1708281732816}]},{"id":8,"name":"г-н Немо","nameHistory":[{"nameChangeId":1,"name":"г-н Немо","date":1708281748476}]},{"id":9,"name":"г-жа Lana","nameHistory":[{"nameChangeId":1,"name":"г-жа Lana","date":1708281809368}]},{"id":10,"name":"г-н Мельдоний","nameHistory":[{"nameChangeId":1,"name":"г-н Мельдоний","date":1708281845861}]},{"id":11,"name":"г-жа Леди Урсула","nameHistory":[{"nameChangeId":1,"name":"г-жа Леди Урсула","date":1708282186250}]},{"id":12,"name":"г-н Вивальди","nameHistory":[{"nameChangeId":1,"name":"г-н Вивальди","date":1708282204292}]},{"id":13,"name":"г-жа White","nameHistory":[{"nameChangeId":1,"name":"г-жа White","date":1708282218030}]},{"id":14,"name":"г-жа Артистка","nameHistory":[{"nameChangeId":1,"name":"г-жа Артистка","date":1708282234766}]},{"id":15,"name":"г-жа Die frau","nameHistory":[{"nameChangeId":1,"name":"г-жа Die frau","date":1708282248742}]},{"id":16,"name":"г-н Ассорти","nameHistory":[{"nameChangeId":1,"name":"г-н Ассорти","date":1708282277721}]},{"id":17,"name":"г-жа Анаконда","nameHistory":[{"nameChangeId":1,"name":"г-жа Анаконда","date":1708282292235}]},{"id":18,"name":"г-н Касторка","nameHistory":[{"nameChangeId":1,"name":"г-н Касторка","date":1708282529588}]},{"id":19,"name":"г-н Арбуз","nameHistory":[{"nameChangeId":1,"name":"г-н Арбуз","date":1708282825933}]},{"id":20,"name":"г-н Хамилка","nameHistory":[{"nameChangeId":1,"name":"г-н Хамилка","date":1708282850077}]},{"id":21,"name":"г-жа Анжи","nameHistory":[{"nameChangeId":1,"name":"г-жа Анжи","date":1708282884714}]},{"id":22,"name":"г-н Дзен","nameHistory":[{"nameChangeId":1,"name":"г-н Дзен","date":1708282927694}]},{"id":23,"name":"г-жа Альбион","nameHistory":[{"nameChangeId":1,"name":"г-жа Альбион","date":1708282956269}]},{"id":24,"name":"г-н Отец Игнатий","nameHistory":[{"nameChangeId":1,"name":"г-н Отец Игнатий","date":1708282987847}]}]}